colorin/__init__.py
colorin/colorin.py
colorin/example.py
colorin/example_graph.py
colorin-0.0.2.dist-info/LICENSE
colorin-0.0.2.dist-info/METADATA
colorin-0.0.2.dist-info/WHEEL
colorin-0.0.2.dist-info/top_level.txt
colorin-0.0.2.dist-info/RECORD
