Metadata-Version: 2.1
Name: colorin
Version: 0.0.2
Summary: Colorea y formatea texto, tablas y gráficas para salida estandar
Home-page: https://github.com/gmolino/colorin
Author: Álvaro García
Author-email: alvaro.garcia.molino@gmail.com
License: UNKNOWN
Platform: UNKNOWN
Classifier: Programming Language :: Python :: 3
Classifier: License :: OSI Approved :: MIT License
Classifier: Operating System :: OS Independent
